missingValues_python/missingValues.py
missingValues_kvarshney_101703295-1.0.3.dist-info/LICENSE
missingValues_kvarshney_101703295-1.0.3.dist-info/METADATA
missingValues_kvarshney_101703295-1.0.3.dist-info/WHEEL
missingValues_kvarshney_101703295-1.0.3.dist-info/entry_points.txt
missingValues_kvarshney_101703295-1.0.3.dist-info/top_level.txt
missingValues_kvarshney_101703295-1.0.3.dist-info/RECORD
