Metadata-Version: 2.1
Name: missingValues-kvarshney-101703295
Version: 1.0.3
Summary: A python package to handle Missing Values using SimpleImputer Class
Home-page: https://github.com/kv6737/missingValues
Author: Kshitiz Varshney
Author-email: kvarshney_be17@thapar.edu
License: UNKNOWN
Platform: UNKNOWN
Classifier: Programming Language :: Python :: 3
Classifier: License :: OSI Approved :: MIT License
Classifier: Operating System :: OS Independent
Requires-Python: >=3.6
Requires-Dist: requests
